hivegraph/__init__.py
hivegraph/augmentations.py
hivegraph/automodel.py
hivegraph/utils.py
hivegraph/configs/__init__.py
hivegraph/configs/classification/__init__.py
hivegraph/configs/classification/gcn.py
hivegraph/configs/classification/gin.py
hivegraph/configs/contrastive/__init__.py
hivegraph/configs/contrastive/grace.py
hivegraph/contrastive/__init__.py
hivegraph/contrastive/grace.py
hivegraph/engine/__init__.py
hivegraph/engine/base.py
hivegraph/engine/classification.py
hivegraph/engine/trainer.py
hivegraph/engine/transductive.py
hivegraph/io/__init__.py
hivegraph/io/autodataset.py
hivegraph/io/transforms.py
hivegraph/nn/__init__.py
hivegraph/nn/gcn.py
hivegraph/nn/gin.py
hivegraph-0.0.2.dist-info/WHEEL
hivegraph-0.0.2.dist-info/METADATA
hivegraph-0.0.2.dist-info/RECORD
